{
    "19010200000208": {
        "基本信息": {
            "出院诊断": "IgA肾病，局灶和节段性肾小球损害，慢性肾脏病1期，高血压",
            "床号": "8551",
            "科别": "肾脏病区",
            "入院时间": "2019-01-02",
            "出院时间": "",
            "姓名": "测试病人0279",
            "性别": "女",
            "年龄": "43",
            "住院号": "z83531",
            "入院诊断": "蛋白尿,高血压"
        },
        "入院时简要病史": "患者于3年前体检时发现尿蛋白（++~+++），无泡沫尿，无尿频、尿急、尿痛，无眼睑及四肢水肿，无口干、多饮，无面部蝶形红斑，无口腔溃疡，无光过敏等表现，院外未做何诊治，每年体检均有尿蛋白阳性，2018-11-20来我院门诊就诊，查尿分析示：蛋白质（++）、红细胞（镜检）6-10/HP；24H尿蛋白定量：1104mg/24h；尿蛋白分型：尿微量白蛋白6.69mg/dl、尿转铁蛋白3.04mg/dl、尿免疫球蛋白G0.96mg/dl、24h尿微量白蛋白80.28mg、24h尿转铁蛋白36.48mg、尿液肌酐8.19mmol/L；血免疫球蛋白测定：IgG 1620mg/dl、IgA 467mg/dl，为进一步行肾穿刺活检术收入院。 患者近期一般情况可，饮食、睡眠可，24h尿量约1.5L，大便正常，体重无明显增减。",
        "体检摘要": "体温36.4℃、脉搏88次/分、呼吸24次/分、血压150/93mmHg。神志清，精神可，两肺呼吸音清，未闻及明显干湿性啰音，心率齐，未闻及病理性杂音，腹软无压痛及反跳痛，肝脾肋下未及，双肾区无叩痛，双下肢无水肿，神经系统检查阴性。",
        "生命体征": {
            "T": "36.4",
            "P": "88",
            "R": "24",
            "BP高": "150",
            "BP低": "93"
        },
        "住院期间医疗情况": "2019-01-03 09:00:57;隐血试验:阴性;白细胞:阴性;红细胞:阴性;虫卵:阴性;性状:软便;2019-01-03 09:02:24;肌钙蛋白I:0.01ng/mL,正常;CK-MB质量:1.2ng/mL,正常;肌红蛋白定量:22.8ng/mL,正常;2019-01-03 09:45:02;红细胞沉降率:9mm/h;2019-01-03 10:44:11;INR:1.03;D-二聚体定量:0.17mg/L,正常;Fg:2.7g/L,正常;PT:12.2秒,正常;TT:18.00秒,正常;APTT:32.8秒,正常;纤维蛋白降解产物:0.6mg/L,正常;2019-01-03 10:48:46;估算肾小球滤过率:93.3ml/min/1.73m2;甘油三酯:0.89mmol/L,正常;总胆红素:12.4μmol/L,正常;磷:1.07mmol/L,正常;钠:142mmol/L,正常;血清镁:0.93mmol/L,正常;脂蛋白(a):0.24g/L,正常;乳酸脱氢酶:156IU/L,正常;钾:4.03mmol/L,正常;总铁结合力:51.6μmol/L,正常;载脂蛋白E:4.3mg/dl,正常;γ-谷氨酰基转移酶:17IU/L,正常;载脂蛋白AI:1.56g/L,正常;总蛋白:67g/L,正常;铁饱和度:26.6％,正常;胆汁酸:1.3μmol/L,正常;高密度脂蛋白胆固醇:1.38mmol/L,正常;血清铁:13.7μmol/L,正常;游离脂肪酸:0.29mmol/L,正常;直接胆红素:2.5μmol/L,正常;肌酐:69μmol/L,正常;二氧化碳:26.0mmol/L,正常;氯:106mmol/L,正常;肌酸激酶:117IU/L,正常;总胆固醇:4.10mmol/L,正常;补体50:47.0U/mL,偏高↑;钙:2.25mmol/L,正常;尿素:3.7mmol/L,正常;天门冬氨酸氨基转移酶:15IU/L,正常;载脂蛋白B:0.79g/L,正常;丙氨酸氨基转移酶:10IU/L,正常;碱性磷酸酶:70IU/L,正常;白球比例:1.48,正常;胆碱酯酶:7030U/L,正常;胱抑素C:0.86mg/L,正常;前白蛋白:283mg/L,正常;尿酸:281μmol/L,正常;低密度脂蛋白胆固醇:2.46mmol/L,正常;2019-01-03 11:18:57;补体C4:16mg/dl,正常;补体C3:80mg/dl,正常;抗链球菌溶血素“O”:29IU/mL,正常;转铁蛋白:182mg/dl,偏低↓;类风湿因子:27IU/mL,偏高↑;轻链κ:9.600g/L,正常;κ/λ轻链比值:2.197,正常;免疫球蛋白IgM:134mg/dl,正常;免疫球蛋白IgG:1110mg/dl,正常;免疫球蛋白IgA:435mg/dl,正常;免疫球蛋白IgE:<5.0IU/mL,正常;2019-01-03 12:13:17;Ig区(百分比):21.30;Ig区(吸光度):45.17;转铁蛋白(百分比):24.40;转铁蛋白(吸光度):51.83;白蛋白(百分比):54.30;白蛋白(吸光度):115.05;结论:肾小球性蛋白尿。;2019-01-03 12:34:33;潜血:弱阳性,正常;葡萄糖:阴性;胆红素:阴性;尿胆元:阴性;酮体:阴性;蛋白质:阳性(+),偏高↑;亚硝酸盐:阴性;酸碱度:6.5,正常;比重:1.014,正常;白细胞:阴性;酵母样菌:阴性;结晶:阴性;小圆上皮细胞:阴性;病理性管型:阴性;白细胞(镜检):0/HP;红细胞(镜检):0/HP;结晶(镜检):阴性;管型(镜检):0/LP,正常;上皮细胞(镜检):0/HP;白细胞计数:4/ul,正常;红细胞计数:31/ul,偏高↑;上皮细胞计数:5/ul,正常;管型计数:0.8/ul,正常;红细胞形态:阴性;2019-01-03 13:39:43;抗中性粒细胞胞浆抗体靶抗原（PR3）:0;抗中性粒细胞胞浆抗体靶抗原（MPO）:0;P-ANCA:阴性;C-ANCA:阴性;2019-01-03 14:05:18;轻链κ:0.035g/L,偏高↑;轻链λ:<0.05g/L,正常;κ/λ轻链比值:0.875;2019-01-03 15:31:13;25羟基维生素D(25-OH-VitD):18.16nmol/L,偏低↓;2019-01-03 15:48:12;艾滋病毒抗体(HIV):阴性;丙肝病毒抗体(HCV-Ab):阴性;2019-01-03 15:55:56;乙肝病毒核心抗体:0.10(-),正常;乙肝病毒e抗原:0.361(-),正常;乙肝病毒e抗体:1.99(-),正常;乙肝病毒表面抗原:0.000(-)IU/mL,正常;乙肝病毒表面抗体:0.92(-)mIU/mL,正常;乙肝病毒核心抗体IgM:0.07(-),正常;2019-01-03 16:14:05;C反应蛋白(高敏)(hsCRP):0.77mg/L,正常;2019-01-03 16:23:41;糖化血红蛋白(HbA1C):5.5％,正常;2019-01-03 16:34:28;降钙素(CT):0.62pg/ml,正常;甲状腺球蛋白抗体(TGAb):0.90IU/mL,正常;甲状腺过氧化物酶抗体(TPOAb):0.32IU/mL,正常;甲状腺素(T4):88.45nmol/L,正常;三碘甲腺原氨酸(T3):1.25nmol/L,正常;促甲状腺素(TSH):1.2579μIU/mL,正常;甲状腺球蛋白:5.470ng/mL,正常;反三碘甲腺原氨酸(rT3):52.40ng/dl,正常;游离甲状腺素(FT4):14.08pmol/L,正常;游离三碘甲腺原氨酸(FT3):3.43pmol/L,正常;2019-01-03 16:53:31;叶酸:10.63ng/mL,正常;抗梅毒螺旋体抗体:0.05,正常;铁蛋白:43.6ng/mL,正常;细胞角蛋白19:1.27ng/mL,正常;癌胚抗原:0.60ng/mL,正常;糖类抗原724:0.72U/mL,正常;糖类抗原242:2.8U/mL,正常;糖类抗原199:4.10U/mL,正常;糖类抗原153:5.20U/mL,正常;糖类抗原125:6.20U/mL,正常;降钙素原:<0.05ng/mL,正常;抗巨细胞病毒IgG:>250.00,偏高↑;维生素B12:440.0pg/mL,正常;鳞状细胞癌相关抗原:0.90ng/mL,正常;梅毒螺旋体RPR:阴性;神经元特异性烯醇化酶:14.37ng/mL,正常;甲胎蛋白:3.13ng/mL,正常;β2-微球蛋白:1368ng/mL,正常;抗弓形虫IgM:0.08,正常;抗弓形虫IgG:0.30,正常;抗风疹病毒IgM:0.42,正常;抗风疹病毒IgG:0.10IU/mL,正常;抗巨细胞病毒IgM:0.39,正常;2019-01-04 10:57:15;24h尿微量白蛋白:418.50mg/24h,偏高↑;24h尿免疫球蛋白G:35.55mg/24h,偏高↑;24h尿A1微球蛋白:9.60mg/24h,正常;尿白蛋白比肌酐:42.21,偏高↑;尿液肌酐:6.61mmol/L;尿转铁蛋白:1.29mg/dl,偏高↑;NAG活性:3.60U/L,正常;尿免疫球蛋白G:2.37mg/dl,偏高↑;尿α1微球蛋白:0.64mg/dl,正常;24h尿转铁蛋白:19.35mg/24h,偏高↑;尿微量白蛋白:27.90mg/dl,偏高↑;尿视黄醇结合蛋白:5.07mg/L,偏高↑;2019-01-04 12:00:31;尿异形红细胞百分率:83％;2019-01-04 12:43:14;抗肾小球基底膜抗体:0,正常;2019-01-04 14:51:23;甲状旁腺激素(PTH):80.3pg/mL,偏高↑;2019-01-04 16:32:33;CD3绝对计数:1805个/μl,正常;CD8绝对计数:655个/μl,正常;CD4绝对计数:1128个/μl,偏高↑;NK:8.2％,偏低↓;CD3^(+)CD8^(+):27.3％,正常;CD3^(+)CD4^(+):47.0％,偏高↑;CD3^(+):75.2％,正常;CD20^(+):17.1;CD19^(+):16.1％,正常;2019-01-04 16:33:23;24H尿尿酸:2.33mmol/24h,正常;24H尿磷:14.64mmol/24h,偏低↓;24H尿钠:109.5mmol/24h,偏低↓;24H尿钾:46.65mmol/24h,正常;24H尿糖:0.20mmol/24h,正常;24H尿氯:124.5mmol/24h,偏低↓;24H尿钙:2.39mmol/24h,偏低↓;24H尿素:240.8mmol/24h,偏低↓;2019-01-04 16:39:43;抗R合胞病毒IgM:阴性;肺支抗体:阴性;抗单纯疱疹病毒Ⅱ型IgM:阴性;抗单纯疱疹病毒Ⅱ型IgG:阴性;抗单纯疱疹病毒Ⅰ型IgM:阴性;抗单纯疱疹病毒Ⅰ型IgG:阳性(+),偏高↑;IgG4:0.08g/L,正常;抗腺病毒IgM:阴性;抗肺炎衣原体IgM:阴性;抗Q热立克次体IgM:阴性;抗军团菌1型IgM:阴性;抗副流1,2,3型IgM:阴性;抗乙流病毒IgM:阴性;抗甲流病毒IgM:阴性;2019-01-04 16:41:11;副流感病毒2 型 (PIV2):阴性;人博卡病毒(HBoV):阴性;肠道病毒(EV):阴性;人鼻病毒(HRV):阴性;人偏肺病毒 (HMPV):阴性;腺病毒 (AdV):阴性;呼吸道合孢病毒B (RSVB):阴性;呼吸道合胞病毒A (RSVA):阴性;冠状病毒229E/NL63型:阴性;冠状病毒OC43型 (CoV OC43):阴性;副流感病毒4 型 (PIV4):阴性;副流感病毒3 型 (PIV3):阴性;副流感病毒1 型 (PIV1):阴性;流行性感冒病毒B 型 (FluB):阴性;流行性感冒病毒A 型 (FluA):阴性;2019-01-04 16:55:50;抗双链DNA IgG(ELISA):33.0IU/mL,正常;2019-01-04 16:57:17;抗组蛋白抗体(印迹法):阴性;抗心磷脂IgG抗体(ELISA):<2GPL/ml,正常;抗环瓜氨酸肽抗体IgG(CLIA):1,正常;抗核抗体(IFA):阴性;抗Jo-1抗体(印迹法):阴性;抗SCL-70抗体(印迹法):阴性;抗SSB抗体(印迹法):阴性;抗SSA抗体(印迹法):阴性;抗Sm抗体(印迹法):阴性;抗RNP/Sm抗体(印迹法):阴性;抗线粒体-M2抗体(印迹法):阴性;抗核糖体P蛋白抗体(印迹法):阴性;抗核小体抗体(印迹法):阴性;抗心磷脂IgA(ELISA):4.4GPL/ml,正常;抗双链DNA抗体(印迹法):弱阳性(±);抗增殖细胞核抗原抗体(印迹法):阴性;抗着丝点蛋白B抗体(印迹法):阴性;抗PM-Scl抗体(印迹法):阴性;抗Ro-52抗体(印迹法):阴性;抗心磷脂IgM(ELISA):<2MPL/ml,正常;2019-01-05 08:30:29;未检出解脲支原体及人型支原体:;2019-01-05 13:23:05;二小时血糖:5.61mmol/L;2019-01-05 14:23:51;真菌培养未生长:,偏高↑;细菌培养二天未生长:,偏高↑;2019-01-05 17:26:25;24H尿量:1.60;24小时尿蛋白:622mg/24h,偏高↑;2019-01-07 13:18:03;抗体筛选结果:阴性;Rh因子:阳性(+)阳性;ABO血型:O型;2019-01-07 15:38:59;白蛋白:48.4％,正常;蛋白电泳:.;γ球蛋白:18.6％,正常;β1球蛋白:18.6％,正常;α2球蛋白:10.3％,正常;α1球蛋白:4.1％,正常;2019-01-07 15:39:02;IgM:阴性;IgA:阴性;IgG:阴性;2019-01-07 15:39:03;免疫固定电泳:.;λ:阴性;κ:阴性;2019-01-08 15:28:39;潜血:阳性(+),偏高↑;红细胞形态:非均一型;上皮细胞计数:5/ul,正常;红细胞计数:83/ul,偏高↑;蛋白质:阳性(+),偏高↑;2019-01-09 09:53:12;I型胶原羧基端肽β特殊序列:0.37;总I型前胶原氨基末端肽:34.74;2019-01-09 10:49:37;单核细胞计数:0.30×10^9/L,正常;嗜酸性粒细胞计数:0.10×10^9/L,正常;嗜碱性粒细胞%:0.9％,正常;嗜碱性粒细胞计数:0.10×10^9/L,正常;红细胞分布宽度:12.6％,正常;红细胞计数:4.32×10^12/L,正常;血小板计数:236×10^9/L,正常;中性粒细胞%:59.0％,正常;中性粒细胞计数:3.90×10^9/L,正常;血小板平均体积:9.9fl,正常;单核细胞%:4.8％,正常;平均红细胞体积:87.6fl,正常;平均血红蛋白浓度:340g/L,正常;平均血红蛋白量:29.7pg,正常;淋巴细胞%:34.5％,正常;淋巴细胞计数:2.30×10^9/L,正常;血红蛋白:129g/L,正常;红细胞比容:0.379,正常;嗜酸性粒细胞%:0.8％,正常;2019-01-09 11:03:58;蛋白质:阴性;2019-01-09 11:04:21;上皮细胞(镜检):3-5/HP;酸碱度:7.5,正常;比重:1.013,正常;白细胞:阴性;酵母样菌:阴性;结晶:阴性;小圆上皮细胞:阴性;病理性管型:阴性;白细胞(镜检):0/HP;红细胞(镜检):4-5/HP;结晶(镜检):阴性;管型(镜检):0/LP,正常;白细胞计数:6/ul,正常;红细胞计数:136/ul,偏高↑;上皮细胞计数:17/ul,偏高↑;管型计数:0.9/ul,正常;清晰度:清晰;颜色:淡黄;红细胞形态:混合型;亚硝酸盐:阴性;蛋白质:阳性(+),偏高↑;酮体:阴性;尿胆元:阴性;潜血:弱阳性,正常;葡萄糖:阴性;胆红素:阴性;2019-01-09 13:49:42;全血粘度:中切(50/s):5.87mpa.s,正常;红细胞压积:0.37,正常;红细胞变形指数:1.06,正常;红细胞刚性指数:9.32,正常;红细胞聚集指数:7.47,正常;血浆粘度:1.32mpa.s,正常;全血还原粘度高切:6.61,正常;全血还原粘度中切:9.31,正常;全血还原粘度低切:17.49,正常;全血粘度:高切(200/s):4.55mpa.s,正常;全血粘度:低切(3/s):9.86mpa.s,正常;2019-01-09 16:20:50;黄体生成素(LH):8.54mIU/mL,正常;卵泡刺激素(FSH):4.71mIU/mL,正常;雌二醇(E2):230.00pg/mL;2019-01-14 11:21:15;白介素-8:26.00pg/mL,正常;白介素-6:3.15pg/mL,正常;白介素-10:<5.00pg/mL,正常;2019-01-03 08:33:29;心电图|常规心电图|心电图|:正常心电图;2019-01-03 09:30:29;超声|彩色超声|彩色超声|肝胆胰脾肾输尿管膀胱US:胆囊隆起样病变（考虑胆囊息肉），随访 肝胰体脾肾膀胱未见明显异常 双侧输尿管未见明显扩张;2019-01-03 14:36:12;超声|常规|心脏超声|心脏US:超声心动图检查未见明显异常;2019-01-04 09:41:53;超声|肾动脉超声|肾动脉超声|双肾及肾动脉US:双肾未见明显异常 双肾动脉血流参数未见明显异常;2019-01-11 15:43:44;超声|彩色超声|彩色超声|腹部US:无分析结果;",
        "出院时情况": "患者一般情况可，生命体征平稳。",
        "病程与治疗情况": "一、肾脏评估： 【肾功能】尿素 3.7mmol/L；肌酐 69μmol/L；尿酸 281μmol/L；估算肾小球滤过率 93.3ml/min/1.73m2 【尿常规】蛋白质 阳性(+)↑； 潜血 弱阳性； 红细胞(镜检) 0/HP 【尿蛋白定量】24小时尿蛋白 622↑mg/24h；24H尿量 1.60 【尿蛋白分型】尿微量白蛋白 27.90↑mg/dl；尿转铁蛋白 1.29↑mg/dl；尿免疫球蛋白G 2.37↑mg/dl；24h尿微量白蛋白 418.50↑mg/24h；24h尿转铁蛋白 19.35↑mg/24h；24h尿免疫球蛋白G 35.55↑mg/24h；尿液肌酐 6.61mmol/L 二、继发因素评估： 【感染】乙肝病毒表面抗原 0.000(-)IU/mL；丙肝病毒抗体(HCV-Ab) 阴性(-)；艾滋病毒抗体(HIV) 阴性(-) 【免疫】免疫球蛋白IgG 1110mg/dl；免疫球蛋白IgA 435mg/dl；免疫球蛋白IgM 134mg/dl；免疫球蛋白IgE &lt;5.0IU/mL；补体C3 80mg/dl；补体C4 16mg/dl；类风湿因子 27↑IU/mL；轻链κ 9.600g/L；轻链λ 4.37g/L 【肿瘤】甲胎蛋白 3.13ng/mL；癌胚抗原 0.60ng/mL；糖类抗原125 6.20U/mL；糖类抗原724 0.72U/mL；糖类抗原199 4.10U/mL；糖类抗原242 2.8U/mL；糖类抗原153 5.20U/mL 【血清免疫】总I型前胶原氨基末端肽 34.74；I型胶原羧基端肽β特殊序列 0.37 三、肾脏病理：光镜所见：肾组织3条，肾小球21-24个，皮质和髓质，2/21-4/24个肾小球球性硬化，1-1个肾小球大细胞纤维新月体形成，1-4个肾小球节段硬化，2-1个肾小球小纤维性新月体形成，0-1个肾小球毛细血管襻与包氏囊粘连，余肾小球部分系膜区系膜基质轻度增多，或伴系膜细胞轻度增生。肾小管间质病变轻度，肾间质轻度灶性纤维增生，较多小灶性炎细胞浸润（以单核细胞、淋巴细胞为主），肾小管轻度灶性萎缩，1条小叶间动脉壁增厚、硬化，个别小叶间动脉灶性透明变性。免疫荧光：肾组织1条，肾小球3-4个。IgA(++)、C3（+~++）、轻链κ（+）/λ （++）：系膜区，颗粒状，弥漫性；IgG、IgM、C1q、Fn：均阴性。诊断：IgA肾病（局灶节段增生硬化）备注：Oxford评分：M0E1S1T0C1，请结合临床。 四、诊疗经过：患者因“蛋白尿3年余”入院，3年前体检时发现尿蛋白（++~+++），无泡沫尿，无尿频、尿急、尿痛。既往有高血压病史，目前应用“奥坦”1粒qd、“倍他乐克”半片qd治疗，血压控制在120/80mmHg。入院后完善相关检查，肾功能：尿素 3.7mmol/L；肌酐 69μmol/L；尿酸 281μmol/L；估算肾小球滤过率 93.3ml/min/1.73m2；尿常规：蛋白质 阳性(+)↑； 潜血 弱阳性； 红细胞(镜检) 0/HP；尿蛋白定量：24小时尿蛋白 622↑mg/24h；24H尿量 1.60；尿蛋白分型：尿微量白蛋白 27.90↑mg/dl；尿转铁蛋白 1.29↑mg/dl；尿免疫球蛋白G 2.37↑mg/dl；24h尿微量白蛋白 418.50↑mg/24h；24h尿转铁蛋白 19.35↑mg/24h；24h尿免疫球蛋白G 35.55↑mg/24h；尿液肌酐 6.61mmol/L。排除禁忌后于2019-01-08行肾穿刺活检术，病理示：IgA肾病（局灶节段增生硬化）Oxford评分：M0E1S1T0C1。经科室讨论，患者肾脏病理显示肾小球硬化比例不高，查24h尿蛋白定量不多，肾功能正常，嘱继续ACEI/ARB口服控制血压降蛋白尿治疗。现患者一般情况可，经上级医师查房后同意办理出院。",
        "出院后用药建议": "1、低盐低脂优质蛋白饮食，注意休息，避免劳累及感染，避免使用肾毒性药物。  \n2、出院带药：奥美沙坦酯片、琥珀酸美托洛尔缓释片。  \n3、门诊随访，定期复查血尿常规、肝肾功能、电解质、血脂、血糖、24小时尿蛋白定量等检查。",
        "病人信息": {
            "姓名": "测试病人0279",
            "性别": "女",
            "科室": "肾脏病区",
            "床号": "8551",
            "住院号": "z83531",
            "住院流水号": "19010200000208",
            "年龄": "43",
            "出生年月": "",
            "入院时间": "2019-01-02",
            "出院时间": ""
        }
    }
}