{
    "患者基本信息": {
        "住院号": "z83531",
        "床号": "8551",
        "入院时间": "2019-01-03",
        "出院时间": "",
        "科室": "乳腺外科一",
        "姓名": "测试病人0279",
        "年龄": "27",
        "性别": "女",
        "低压(BP低)": "70",
        "高压(BP高)": "120",
        "脉搏(P)": "72",
        "呼吸(R)": "16",
        "体温(T)": "36.8",
        "入院诊断": "乳房肿块(右乳)",
        "入院时简要病史": [
            "患者3个月前体检发现右乳一肿物，大小约2cm。",
            "活动度好，无压痛，无乳房局部皮肤破溃红肿，皮肤无变薄，皮下未见扩张静脉，乳头皮肤无湿疹样改变。",
            "无乳头溢液。",
            "2019-01-03隧至我院门诊就诊，乳腺B超提示：右侧乳腺可见一低回声，位于约8点钟方向腺体边缘，大小约24×13mm，水平位生长，呈分叶状，拟US-BI-RADS 3类。",
            "本次为行进一步诊治，门诊拟“右乳肿物”收治入院。",
            "     自发病以来，患者神清，精神可，睡眠胃纳可，二便正常，体重无明显增减。"
        ],
        "体检摘要": [
            "查体：双乳对称；双乳皮肤无红肿、破溃、凹陷、橘皮样变；双侧乳头等高、无凹陷、无歪斜，无乳头湿疹样改变，未见陈旧手术疤痕；右乳外下可扪及一直径约2cm肿块，质地硬，活动度好，边界清楚，肿块与皮肤无粘连，无明显触痛。",
            "无溢液。",
            "对侧乳腺未及明确肿块。",
            "双侧腋窝及双侧锁骨上不可扪及异常肿大淋巴结。"
        ]
    },
    "住院期间医疗情况": [
        "2019-01-03 12:03:12;APTT:34.6秒,正常;PT:11.8秒,正常;INR:1.00;",
        "2019-01-03 12:12:09;血小板平均体积:10.6fl,正常;血小板计数:366×10^9/L,偏高↑;嗜酸性粒细胞%:0.4％,偏低↓;",
        "2019-01-03 12:51:21;平均血红蛋白量:29.7pg,正常;血小板平均体积:12.7fl,偏高↑;血小板计数:203×10^9/L,正常;红细胞分布宽度:12.4％,正常;平均血红蛋白浓度:341g/L,正常;平均红细胞体积:87.1fl,正常;白细胞计数:5.38x10^9/L,正常;红细胞比容:0.460,正常;血红蛋白:157g/L,正常;红细胞计数:5.28×10^12/L,正常;单核细胞计数:0.34×10^9/L,正常;嗜碱性粒细胞计数:0.03×10^9/L,正常;嗜酸性粒细胞计数:0.08×10^9/L,正常;淋巴细胞计数:1.89×10^9/L,正常;中性粒细胞计数:3.04×10^9/L,正常;嗜碱性粒细胞%:0.6％,正常;嗜酸性粒细胞%:1.5％,正常;单核细胞%:6.3％,正常;淋巴细胞%:35.1％,正常;中性粒细胞%:56.5％,正常;",
        "2019-01-03 12:52:32;磷:1.11mmol/L,正常;钠:141mmol/L,正常;钾:4.29mmol/L,正常;肌酐:51μmol/L,偏低↓;丙氨酸氨基转移酶:9IU/L,偏低↓;二氧化碳:28.1mmol/L,正常;氯:104mmol/L,正常;钙:2.42mmol/L,正常;",
        "2019-01-03 13:57:33;游离脂肪酸:0.55mmol/L,偏高↑;肌酐:73μmol/L,正常;总胆固醇:4.50mmol/L,正常;尿素:4.1mmol/L,正常;天门冬氨酸氨基转移酶:32IU/L,正常;载脂蛋白B:0.77g/L,正常;丙氨酸氨基转移酶:23IU/L,正常;碱性磷酸酶:85IU/L,正常;白蛋白:48g/L,正常;脂蛋白(a):0.07g/L,正常;直接胆红素:2.0μmol/L,正常;载脂蛋白AI:1.60g/L,正常;γ-谷氨酰基转移酶:14IU/L,正常;白球比例:1.55,正常;胱抑素C:0.89mg/L,正常;前白蛋白:301mg/L,正常;尿酸:330μmol/L,正常;低密度脂蛋白胆固醇:2.73mmol/L,正常;高密度脂蛋白胆固醇:1.40mmol/L,正常;胆汁酸:6.3μmol/L,正常;总蛋白:79g/L,正常;甘油三酯:1.69mmol/L,正常;总胆红素:12.8μmol/L,正常;甘胆酸:0.77mg/L,正常;小而密低密度脂蛋白胆固醇:0.820mmol/L,正常;葡萄糖:4.79mmol/L,正常;载脂蛋白E:4.3mg/dl,正常;估算肾小球滤过率:115.9ml/min/1.73m2;",
        "2019-01-03 15:10:32;甲胎蛋白:1.42ng/mL,正常;",
        "2019-01-03 15:49:34;艾滋病毒抗体(HIV):阴性;丙肝病毒抗体(HCV-Ab):阴性;",
        "2019-01-03 16:40:29;抗梅毒螺旋体抗体:0.07,正常;梅毒螺旋体RPR:阴性;",
        "2019-01-04 09:46:18;乙肝病毒表面抗原:0.000(-)IU/mL,正常;乙肝病毒核心抗体IgM:0.10(-),正常;乙肝病毒核心抗体:0.08(-),正常;",
        "2019-01-04 11:58:27;乙肝病毒e抗原:0.318(-),正常;乙肝病毒e抗体:1.04(-),正常;乙肝病毒表面抗原:194.280(+)IU/mL,偏高↑;乙肝病毒表面抗体:0.00(-)mIU/mL,正常;乙肝病毒S蛋白定量:194.28(+)IU/mL,偏高↑;",
        "2019-01-04 14:47:26;乙肝病毒核酸定量(PCR):<5.00×10^2 IU/mlIU/mL;",
        "2019-01-03 12:30:02;心电图|常规心电图|心电图|:正常心电图;",
        "2019-01-03 12:49:45;放射|胸部|X-ray平片|胸部 胸部:两肺未见明显异常。请结合临床、病史及其他检查，随访。;",
        "2019-01-03 14:10:56;超声|常规|US|肝胆胰脾肾US:肝胆囊胰体脾肾未见明显异常;"
    ],
    "出院诊断": "乳房良性肿瘤(右乳待石蜡)",
    "病程与治疗情况": [
        "患者入院后完善相关检查，排除手术禁忌后，于2019-01-03全麻下行右乳肿块麦默通旋切术，术后石蜡病理未回。",
        "现患者一般情况良好，伤口愈合I/甲，经上级医师查房同意后，予以出院。"
    ],
    "出院后用药建议": [
        "1. 10个工作日后来院询问石蜡病理报告，并带至主诊医师门诊就诊，拟定进一步诊疗或随访方案。",
        "  \n",
        "2. 术后胸带加压包扎切口5天；之后可佩戴文胸；保持伤口清洁干燥，2周内避免洗澡；术后10天内每3天来院换药一次。",
        "  \n",
        "3. 保持伤口清洁干燥，如有发热，切口局部红肿、疼痛、化脓等不适，及时来院就诊。",
        "  \n",
        "4. 患者住院期间肝功能检查游离脂肪酸。",
        "0.55↑mmol/L，建议至消化科随访。",
        "  \n",
        "5. 患者术后康复评估见专页。"
    ],
    "出院时情况": [
        "神清，精神可，一般情况良好。",
        "伤口愈合I/甲。"
    ]
}